csvmorph/__init__.py
csvmorph/analyze_csv.py
csvmorph/cli.py
csvmorph/csvmorph.py
csvmorph/helpers.py
csvmorph/json_streamer.cpp
csvmorph/json_streamer.cpython-35m-x86_64-linux-gnu.so
csvmorph/json_streamer.pyx
csvmorph/parser.cpp
csvmorph/parser.cpython-35m-x86_64-linux-gnu.so
csvmorph/parser.pyx
csvmorph/testing.py
csvmorph/csv-parser/src/csv_parser.hpp
csvmorph/csv-parser/src/csv_stat.hpp
csvmorph/csv-parser/src/csvmorph.hpp
csvmorph/csv-parser/src/data_type.hpp
csvmorph/csv-parser/src/json_streamer.hpp
csvmorph/csv-parser/tests/catch.hpp
csvmorph/csv-parser/tests/test_csv_clean.cpp
csvmorph/csv-parser/tests/test_csv_stat.cpp
csvmorph/csv-parser/tests/test_data_type.cpp
csvmorph/csv-parser/tests/test_read_csv.cpp
csvmorph/json/__init__.py
csvmorph/json/json_loads_hooks.py
csvmorph-1.0.1a8.dist-info/DESCRIPTION.rst
csvmorph-1.0.1a8.dist-info/METADATA
csvmorph-1.0.1a8.dist-info/RECORD
csvmorph-1.0.1a8.dist-info/WHEEL
csvmorph-1.0.1a8.dist-info/entry_points.txt
csvmorph-1.0.1a8.dist-info/metadata.json
csvmorph-1.0.1a8.dist-info/top_level.txt
