Metadata-Version: 2.0
Name: csvmorph
Version: 1.0.1a8
Summary: A fast library for manipulating and CSV files
Home-page: https://github.com/vincentlaucsb/csvmorph/
Author: Vincent La
Author-email: vincela9@gmail.com
License: MIT
Keywords: convert txt csv json text delimited
Platform: UNKNOWN
Classifier: Development Status :: 3 - Alpha
Classifier: Programming Language :: Python :: 3.3
Classifier: Programming Language :: Python :: 3.4
Classifier: Programming Language :: Python :: 3.5
Classifier: Programming Language :: Python :: 3.6
Classifier: Intended Audience :: Developers
Classifier: License :: OSI Approved :: MIT License
Classifier: Topic :: Scientific/Engineering :: Information Analysis
Requires-Dist: Click
